EyesLibrary/PropagateEyesTestResults.py
EyesLibrary/__init__.py
EyesLibrary/__main__.py
EyesLibrary/__version__.py
EyesLibrary/applitools.yaml
EyesLibrary/base.py
EyesLibrary/config.py
EyesLibrary/config_parser.py
EyesLibrary/custom_types.py
EyesLibrary/errors.py
EyesLibrary/eyes_cache.py
EyesLibrary/keywords_list.py
EyesLibrary/library_listener.py
EyesLibrary/locator_converter.py
EyesLibrary/py.typed
EyesLibrary/robot_patcher.py
EyesLibrary/test_results_manager.py
EyesLibrary/utils.py
EyesLibrary/keywords/__init__.py
EyesLibrary/keywords/check.py
EyesLibrary/keywords/check_settings.py
EyesLibrary/keywords/config.py
EyesLibrary/keywords/keyword_tags.py
EyesLibrary/keywords/session.py
EyesLibrary/keywords/target.py
EyesLibrary/keywords/target_path.py
eyes_robotframework-6.4.18.dist-info/licenses/LICENSE
eyes_robotframework-6.4.18.dist-info/METADATA
eyes_robotframework-6.4.18.dist-info/WHEEL
eyes_robotframework-6.4.18.dist-info/top_level.txt
eyes_robotframework-6.4.18.dist-info/RECORD
