Metadata-Version: 2.4
Name: eyes-robotframework
Version: 6.4.18
Summary: Applitools Python SDK. Robot Framework package
Author-email: Applitools Team <team@applitools.com>
License-Expression: LicenseRef-Proprietary
Project-URL: Homepage, https://applitools.com
Keywords: applitools,robotframework,eyes,eyes_selenium,selenium,appium
Classifier: Development Status :: 5 - Production/Stable
Classifier: Framework :: Robot Framework :: Library
Classifier: Intended Audience :: Developers
Classifier: Programming Language :: Python
Classifier: Topic :: Software Development :: Quality Assurance
Classifier: Topic :: Software Development :: Testing
Requires-Python: <4,>=3.7
License-File: LICENSE
Requires-Dist: PyYAML!=5.4.0,!=5.4.1,!=6.0.0,<7,>=5
Requires-Dist: eyes-selenium==6.4.18
Requires-Dist: robotframework-appiumlibrary>=1.6.1
Requires-Dist: Appium-Python-Client<4
Requires-Dist: robotframework-pythonlibcore>=3.0
Requires-Dist: robotframework-seleniumlibrary>=4.5
Requires-Dist: robotframework>=4.0
Requires-Dist: trafaret==2.1.0
Requires-Dist: yamllint<2.0,>1.25.0
Dynamic: license-file
